pi_core/__init__.py
pi_core/enum.py
pi_core/settings.py
pi_core/validators.py
pi_core/dependencies/school.py
pi_core/dependencies/user.py
pi_core/middleware/__init__.py
pi_core/middleware/user_context.py
pi_core/models/pupil.py
pi_core/models/school.py
pi_core/models/user.py
pi_core/tests/__init__.py
pi_core/tests/test_models.py
pi_core/utils/validators.py
pi_core-0.1.0.1.dist-info/METADATA
pi_core-0.1.0.1.dist-info/WHEEL
pi_core-0.1.0.1.dist-info/top_level.txt
pi_core-0.1.0.1.dist-info/RECORD
