Metadata-Version: 2.4
Name: pi-core
Version: 0.1.0.1
Summary: Shared core models and utilities for the PI Platform
Author-email: Possible Institute <support@possible.institute>
License: MIT
Project-URL: Homepage, https://github.com/Possible-Institute/pi-core
Requires-Python: >=3.8
Requires-Dist: pydantic>=2.0
